speech_tool/__init__.py
speech_tool/config.py
speech_tool/kokoro_server.py
speech_tool-0.0.8.dist-info/LICENSE
speech_tool-0.0.8.dist-info/METADATA
speech_tool-0.0.8.dist-info/WHEEL
speech_tool-0.0.8.dist-info/RECORD
