Metadata-Version: 2.1
Name: speech_tool
Version: 0.0.8
Summary: 
Author: C. Thomas Brittain
Author-email: cthomasbrittain@hotmail.com
Requires-Python: >=3.10,<3.13
Classifier: Programming Language :: Python :: 3
Classifier: Programming Language :: Python :: 3.10
Classifier: Programming Language :: Python :: 3.11
Classifier: Programming Language :: Python :: 3.12
Requires-Dist: fastapi[standard] (>=0.115.8,<0.116.0)
Requires-Dist: kokoro-onnx (>=0.4.0,<0.5.0)
Requires-Dist: poethepoet (>=0.32.2,<0.33.0)
Requires-Dist: pyyaml (>=6.0.2,<7.0.0)
Requires-Dist: sounddevice (>=0.5.1,<0.6.0)
Requires-Dist: soundfile (>=0.13.1,<0.14.0)
